{
  "idShort": "MultiSubmodel_1",
  "identification": {
    "id": "urn:org.eclipse.basyx:submodels:MultiSubmodel_1:1.0.0",
    "idType": "IRI"
  },
  "administration": {
    "version": "1.0",
    "revision": "120"
  },
  "description": [
    {
      "language": "de",
      "text": "1. Teilmodell"
    },
    {
      "language": "en",
      "text": "1. Submodel"
    }
  ],
  "endpoints": [
    {
      "address": "http://127.0.0.1:6999/submodels/MultiSubmodel_1/submodel",
      "type": "http"
    },
    {
      "address": "https://127.0.0.1:6499/submodels/MultiSubmodel_1/submodel",
      "type": "https"
    }
  ],
  "modelType": {
    "name": "SubmodelDescriptor"
  }
}